{
    "info": {
        "description": "2D pose estimation outputs from NTU_RGB+D_120",
        "url": "",
        "version": "1.0",
        "year": 2024,
        "contributor": "cacaoBrain-HumanCV",
        "date_created": "2024-03-26 11:28:56"
    },
    "video": {
        "path": "./NTU_DATASET/A065/S029C002P008R002A065_rgb.avi",
        "width": 1920,
        "height": 1080,
        "original_length": 36,
        "fps": 30.0
    },
    "annotations": [
        {
            "0": [
                [
                    445.323486328125,
                    1049.8123779296875,
                    0.9661355018615723
                ],
                [
                    437.3094177246094,
                    1065.147216796875,
                    0.9663647413253784
                ],
                [
                    430.55535888671875,
                    1039.634521484375,
                    0.933104395866394
                ],
                [
                    444.7386779785156,
                    1080.7255859375,
                    0.973625898361206
                ],
                [
                    428.3681945800781,
                    1021.5494384765625,
                    0.9664551019668579
                ],
                [
                    504.92529296875,
                    1091.4583740234375,
                    0.8576871752738953
                ],
                [
                    467.8101501464844,
                    980.65185546875,
                    0.8736552000045776
                ],
                [
                    571.9644775390625,
                    1104.029296875,
                    0.9270578026771545
                ],
                [
                    528.258544921875,
                    955.6467895507812,
                    0.9261289238929749
                ],
                [
                    638.5052490234375,
                    1068.640625,
                    0.9172624945640564
                ],
                [
                    597.0667724609375,
                    951.440673828125,
                    0.9772461652755737
                ],
                [
                    614.77197265625,
                    1048.605712890625,
                    0.831821620464325
                ],
                [
                    599.381103515625,
                    982.5982666015625,
                    0.8097365498542786
                ],
                [
                    710.59130859375,
                    1055.0828857421875,
                    0.8776043057441711
                ],
                [
                    687.3018798828125,
                    940.6653442382812,
                    0.9113970398902893
                ],
                [
                    763.0216064453125,
                    1067.238525390625,
                    0.9488214254379272
                ],
                [
                    739.8086547851562,
                    968.4049072265625,
                    0.910035252571106
                ]
            ]
        },
        {
            "0": [
                [
                    445.80865478515625,
                    1052.1944580078125,
                    0.9663474559783936
                ],
                [
                    437.4270935058594,
                    1068.176513671875,
                    0.9752271771430969
                ],
                [
                    430.910888671875,
                    1042.218017578125,
                    0.9436065554618835
                ],
                [
                    443.7301940917969,
                    1084.369140625,
                    0.9551860094070435
                ],
                [
                    427.8685302734375,
                    1024.8973388671875,
                    0.9727756977081299
                ],
                [
                    505.0640869140625,
                    1094.5438232421875,
                    0.860461950302124
                ],
                [
                    466.57659912109375,
                    984.2632446289062,
                    0.8542120456695557
                ],
                [
                    571.9885864257812,
                    1109.1484375,
                    0.9584096074104309
                ],
                [
                    525.372314453125,
                    959.7158203125,
                    0.9412245154380798
                ],
                [
                    638.60546875,
                    1070.888427734375,
                    0.9185634851455688
                ],
                [
                    590.185546875,
                    951.92626953125,
                    0.964867353439331
                ],
                [
                    616.1069946289062,
                    1050.4267578125,
                    0.8430829644203186
                ],
                [
                    598.18017578125,
                    983.860595703125,
                    0.8130597472190857
                ],
                [
                    709.9352416992188,
                    1054.350830078125,
                    0.8803489804267883
                ],
                [
                    687.163330078125,
                    942.1661376953125,
                    0.9069874286651611
                ],
                [
                    762.4127807617188,
                    1067.01953125,
                    0.9574458599090576
                ],
                [
                    739.829833984375,
                    968.6644287109375,
                    0.9336726069450378
                ]
            ]
        },
        {
            "0": [
                [
                    446.1249084472656,
                    1052.43212890625,
                    0.9742074012756348
                ],
                [
                    437.9107666015625,
                    1068.131103515625,
                    0.9764071106910706
                ],
                [
                    431.45147705078125,
                    1042.415771484375,
                    0.9462850093841553
                ],
                [
                    445.2296142578125,
                    1085.276611328125,
                    0.9830966591835022
                ],
                [
                    428.8392333984375,
                    1025.57958984375,
                    0.961933434009552
                ],
                [
                    508.00323486328125,
                    1096.655517578125,
                    0.8271046876907349
                ],
                [
                    465.6141357421875,
                    987.15771484375,
                    0.8617456555366516
                ],
                [
                    572.8603515625,
                    1112.0306396484375,
                    0.9506499767303467
                ],
                [
                    523.4447021484375,
                    962.2684936523438,
                    0.9071228504180908
                ],
                [
                    639.388427734375,
                    1073.046630859375,
                    0.9375921487808228
                ],
                [
                    589.5983276367188,
                    954.2076416015625,
                    0.9613927006721497
                ],
                [
                    614.3724365234375,
                    1052.201416015625,
                    0.8440736532211304
                ],
                [
                    595.4537353515625,
                    986.3743286132812,
                    0.812806248664856
                ],
                [
                    710.8175048828125,
                    1058.34814453125,
                    0.8914576768875122
                ],
                [
                    685.543701171875,
                    943.6455078125,
                    0.9306166172027588
                ],
                [
                    762.3896484375,
                    1067.14599609375,
                    0.9498159289360046
                ],
                [
                    739.8714599609375,
                    968.6561279296875,
                    0.9416937828063965
                ]
            ]
        },
        {
            "0": [
                [
                    449.97601318359375,
                    1049.8658447265625,
                    0.9618329405784607
                ],
                [
                    441.26434326171875,
                    1065.6973876953125,
                    0.9793155193328857
                ],
                [
                    434.88824462890625,
                    1039.58935546875,
                    0.9737030267715454
                ],
                [
                    448.4734191894531,
                    1084.1583251953125,
                    0.9771731495857239
                ],
                [
                    431.8846435546875,
                    1023.9945068359375,
                    0.9687215089797974
                ],
                [
                    511.8727111816406,
                    1097.005859375,
                    0.8261218070983887
                ],
                [
                    468.2513732910156,
                    987.95703125,
                    0.8766130208969116
                ],
                [
                    581.4004516601562,
                    1107.830078125,
                    0.943803071975708
                ],
                [
                    525.6262817382812,
                    964.55029296875,
                    0.9312146306037903
                ],
                [
                    646.9636840820312,
                    1067.83740234375,
                    0.9482125639915466
                ],
                [
                    590.5279541015625,
                    957.2094116210938,
                    0.9636741280555725
                ],
                [
                    617.718994140625,
                    1054.2152099609375,
                    0.8520538806915283
                ],
                [
                    598.6751098632812,
                    989.5742797851562,
                    0.8252443075180054
                ],
                [
                    714.8331298828125,
                    1061.016357421875,
                    0.8575632572174072
                ],
                [
                    685.8286743164062,
                    942.7882080078125,
                    0.9316843152046204
                ],
                [
                    762.5969848632812,
                    1066.3798828125,
                    0.9502590894699097
                ],
                [
                    740.006103515625,
                    968.1948852539062,
                    0.9402350187301636
                ]
            ]
        },
        {
            "0": [
                [
                    448.9664306640625,
                    1047.582275390625,
                    0.9572793841362
                ],
                [
                    439.1459655761719,
                    1063.711669921875,
                    0.9595334529876709
                ],
                [
                    433.6876525878906,
                    1036.61328125,
                    0.998315691947937
                ],
                [
                    445.01470947265625,
                    1082.98876953125,
                    0.9464086890220642
                ],
                [
                    430.8618469238281,
                    1022.3933715820312,
                    0.9638617038726807
                ],
                [
                    518.7073364257812,
                    1092.8662109375,
                    0.8038811087608337
                ],
                [
                    461.32537841796875,
                    995.6430053710938,
                    0.8989734649658203
                ],
                [
                    590.908447265625,
                    1088.7052001953125,
                    0.957925021648407
                ],
                [
                    513.838623046875,
                    977.0484619140625,
                    0.9093140363693237
                ],
                [
                    613.1167602539062,
                    1016.4747924804688,
                    0.9366902112960815
                ],
                [
                    580.4728393554688,
                    964.4989013671875,
                    0.9330546855926514
                ],
                [
                    617.2488403320312,
                    1057.46484375,
                    0.8418803811073303
                ],
                [
                    595.77197265625,
                    993.1497192382812,
                    0.8085400462150574
                ],
                [
                    716.5963745117188,
                    1064.554931640625,
                    0.8431649804115295
                ],
                [
                    684.6279296875,
                    945.97216796875,
                    0.933198869228363
                ],
                [
                    762.46630859375,
                    1066.8746337890625,
                    0.9486321806907654
                ],
                [
                    739.7191162109375,
                    968.3126220703125,
                    0.9408385753631592
                ]
            ]
        },
        {
            "0": [
                [
                    448.0275573730469,
                    1038.23388671875,
                    1.008252501487732
                ],
                [
                    438.8558044433594,
                    1055.4228515625,
                    0.9613634943962097
                ],
                [
                    432.28826904296875,
                    1029.0322265625,
                    0.9767143726348877
                ],
                [
                    436.35284423828125,
                    1079.7215576171875,
                    0.9836374521255493
                ],
                [
                    418.766357421875,
                    1019.893798828125,
                    0.8909736275672913
                ],
                [
                    503.16729736328125,
                    1076.2042236328125,
                    0.8314781188964844
                ],
                [
                    443.4771423339844,
                    1011.3656616210938,
                    0.9258633255958557
                ],
                [
                    581.9234008789062,
                    1030.5225830078125,
                    0.9432028532028198
                ],
                [
                    504.4610595703125,
                    1000.4503173828125,
                    0.8608839511871338
                ],
                [
                    535.207275390625,
                    970.7894287109375,
                    0.9407816529273987
                ],
                [
                    557.933349609375,
                    983.497314453125,
                    0.8877885341644287
                ],
                [
                    619.430419921875,
                    1059.982421875,
                    0.8226689696311951
                ],
                [
                    595.2047119140625,
                    1004.3397216796875,
                    0.8285971879959106
                ],
                [
                    717.0167236328125,
                    1061.256591796875,
                    0.8385847806930542
                ],
                [
                    676.2601318359375,
                    951.7870483398438,
                    0.963916003704071
                ],
                [
                    763.321533203125,
                    1066.7337646484375,
                    0.9358533620834351
                ],
                [
                    738.2635498046875,
                    968.2833862304688,
                    0.9411396980285645
                ]
            ]
        },
        {
            "0": [
                [
                    461.64361572265625,
                    1012.5947875976562,
                    0.9520785808563232
                ],
                [
                    455.19500732421875,
                    1029.6025390625,
                    0.9661420583724976
                ],
                [
                    446.3382263183594,
                    1006.7131958007812,
                    0.9712997078895569
                ],
                [
                    449.01885986328125,
                    1064.102783203125,
                    0.9995444416999817
                ],
                [
                    428.63580322265625,
                    1003.2925415039062,
                    0.838897168636322
                ],
                [
                    507.5081787109375,
                    1057.7767333984375,
                    0.8582854866981506
                ],
                [
                    457.19964599609375,
                    1041.81640625,
                    0.5613241195678711
                ],
                [
                    576.6270751953125,
                    983.1735229492188,
                    0.9681560397148132
                ],
                [
                    506.5543518066406,
                    1034.066650390625,
                    0.49593475461006165
                ],
                [
                    520.58544921875,
                    953.2594604492188,
                    1.0117793083190918
                ],
                [
                    493.1698303222656,
                    993.2041625976562,
                    0.58782958984375
                ],
                [
                    624.3945922851562,
                    1063.316162109375,
                    0.7572538256645203
                ],
                [
                    596.430419921875,
                    1015.063232421875,
                    0.8021795749664307
                ],
                [
                    724.0365600585938,
                    1052.64208984375,
                    0.8501261472702026
                ],
                [
                    668.8563842773438,
                    958.1550903320312,
                    0.9346626400947571
                ],
                [
                    763.6447143554688,
                    1065.2799072265625,
                    0.9528478980064392
                ],
                [
                    736.9818115234375,
                    969.1770629882812,
                    0.9255085587501526
                ]
            ]
        },
        {
            "0": [
                [
                    489.4198303222656,
                    996.7490234375,
                    1.0245152711868286
                ],
                [
                    481.6500244140625,
                    1013.7160034179688,
                    0.9720708727836609
                ],
                [
                    472.3648376464844,
                    989.549072265625,
                    0.9806674122810364
                ],
                [
                    474.417724609375,
                    1046.705810546875,
                    1.0632420778274536
                ],
                [
                    453.67034912109375,
                    985.8690185546875,
                    0.9096853733062744
                ],
                [
                    528.6466674804688,
                    1040.378173828125,
                    0.8064168095588684
                ],
                [
                    464.97174072265625,
                    1048.9144287109375,
                    0.6195992231369019
                ],
                [
                    605.1024169921875,
                    977.4752197265625,
                    0.9812750816345215
                ],
                [
                    515.10009765625,
                    1030.08154296875,
                    0.35461103916168213
                ],
                [
                    554.19384765625,
                    955.4447631835938,
                    0.9621507525444031
                ],
                [
                    521.550048828125,
                    1000.7603759765625,
                    0.7019126415252686
                ],
                [
                    634.120849609375,
                    1073.3001708984375,
                    0.7342172861099243
                ],
                [
                    604.91015625,
                    1028.618896484375,
                    0.7775248885154724
                ],
                [
                    738.516357421875,
                    1050.7547607421875,
                    0.8861706852912903
                ],
                [
                    669.0953979492188,
                    960.035888671875,
                    0.9105345606803894
                ],
                [
                    765.6704711914062,
                    1066.284423828125,
                    0.9400169849395752
                ],
                [
                    737.2333984375,
                    968.9742431640625,
                    0.9254013895988464
                ]
            ]
        },
        {
            "0": [
                [
                    495.5035400390625,
                    999.059814453125,
                    0.997116208076477
                ],
                [
                    486.1260681152344,
                    1015.9263916015625,
                    0.9429835081100464
                ],
                [
                    480.2156677246094,
                    991.9298095703125,
                    0.9701826572418213
                ],
                [
                    483.1247863769531,
                    1045.525146484375,
                    1.0267577171325684
                ],
                [
                    467.7839050292969,
                    984.6920166015625,
                    0.8590101003646851
                ],
                [
                    533.7359008789062,
                    1045.84033203125,
                    0.7821314930915833
                ],
                [
                    488.71624755859375,
                    1035.980712890625,
                    0.466163694858551
                ],
                [
                    623.4434814453125,
                    1005.508056640625,
                    0.9392560720443726
                ],
                [
                    552.0184326171875,
                    1034.05078125,
                    0.505201518535614
                ],
                [
                    626.10595703125,
                    955.6773071289062,
                    0.940940797328949
                ],
                [
                    583.6788940429688,
                    1008.2157592773438,
                    0.8437023758888245
                ],
                [
                    646.313720703125,
                    1077.2664794921875,
                    0.7557542324066162
                ],
                [
                    623.5634155273438,
                    1031.7626953125,
                    0.7523466348648071
                ],
                [
                    749.436767578125,
                    1051.658935546875,
                    0.888538122177124
                ],
                [
                    673.422119140625,
                    953.910888671875,
                    0.9088243842124939
                ],
                [
                    768.5787353515625,
                    1066.678955078125,
                    0.9123968482017517
                ],
                [
                    738.4913330078125,
                    968.5474243164062,
                    0.9246475100517273
                ]
            ]
        },
        {
            "0": [
                [
                    471.5487365722656,
                    1018.4575805664062,
                    0.971767246723175
                ],
                [
                    460.41119384765625,
                    1033.619873046875,
                    0.9887766242027283
                ],
                [
                    458.08062744140625,
                    1006.6466674804688,
                    0.9752860069274902
                ],
                [
                    463.3692932128906,
                    1054.49658203125,
                    0.9538902044296265
                ],
                [
                    457.6378479003906,
                    992.8679809570312,
                    0.960519015789032
                ],
                [
                    513.1170654296875,
                    1060.912841796875,
                    0.8480420708656311
                ],
                [
                    495.00677490234375,
                    1009.083251953125,
                    0.7695943117141724
                ],
                [
                    573.3555297851562,
                    1022.7755737304688,
                    0.7757799625396729
                ],
                [
                    553.0131225585938,
                    1007.7001342773438,
                    0.8253626823425293
                ],
                [
                    619.5640869140625,
                    974.2139892578125,
                    0.7600908875465393
                ],
                [
                    609.6160888671875,
                    990.4882202148438,
                    0.6767709255218506
                ],
                [
                    652.37255859375,
                    1076.4970703125,
                    0.7767241597175598
                ],
                [
                    624.4094848632812,
                    1027.7247314453125,
                    0.8151702284812927
                ],
                [
                    752.60400390625,
                    1049.745361328125,
                    0.8774611949920654
                ],
                [
                    678.1202392578125,
                    954.3780517578125,
                    0.8906433582305908
                ],
                [
                    770.3470458984375,
                    1067.3961181640625,
                    0.9005618691444397
                ],
                [
                    739.4974975585938,
                    967.6988525390625,
                    0.9212868809700012
                ]
            ]
        },
        {
            "0": [
                [
                    434.63818359375,
                    1030.093017578125,
                    0.9804444313049316
                ],
                [
                    427.5694885253906,
                    1045.2841796875,
                    0.9753478169441223
                ],
                [
                    422.6216735839844,
                    1018.8642578125,
                    0.9993427395820618
                ],
                [
                    439.6654968261719,
                    1061.866943359375,
                    0.9121140241622925
                ],
                [
                    430.1896057128906,
                    1000.93212890625,
                    0.9555082321166992
                ],
                [
                    482.88458251953125,
                    1062.98388671875,
                    0.8347654938697815
                ],
                [
                    481.13031005859375,
                    1002.5034790039062,
                    0.9448457956314087
                ],
                [
                    454.7335205078125,
                    1085.1591796875,
                    0.9374641180038452
                ],
                [
                    528.0928344726562,
                    999.6534423828125,
                    0.9181544780731201
                ],
                [
                    407.6801452636719,
                    1111.210205078125,
                    0.9187131524085999
                ],
                [
                    588.5673828125,
                    977.8419799804688,
                    0.9506064653396606
                ],
                [
                    643.2889404296875,
                    1075.8564453125,
                    0.8062654137611389
                ],
                [
                    619.662841796875,
                    1026.3621826171875,
                    0.8656571507453918
                ],
                [
                    751.7645263671875,
                    1050.087158203125,
                    0.8632652163505554
                ],
                [
                    674.5771484375,
                    955.031494140625,
                    0.927966296672821
                ],
                [
                    770.57177734375,
                    1069.4185791015625,
                    0.9418846368789673
                ],
                [
                    739.6926879882812,
                    968.269775390625,
                    0.9392596483230591
                ]
            ]
        },
        {
            "0": [
                [
                    398.8345031738281,
                    1048.615478515625,
                    0.9561301469802856
                ],
                [
                    393.9375915527344,
                    1064.318115234375,
                    1.004915714263916
                ],
                [
                    387.2371826171875,
                    1038.40966796875,
                    0.9638055562973022
                ],
                [
                    410.5435485839844,
                    1077.2567138671875,
                    0.8531665802001953
                ],
                [
                    396.9266357421875,
                    1017.9794921875,
                    0.9345782995223999
                ],
                [
                    455.7213134765625,
                    1076.99169921875,
                    0.9045259356498718
                ],
                [
                    455.23199462890625,
                    1007.9083251953125,
                    0.9706498980522156
                ],
                [
                    419.28936767578125,
                    1115.630615234375,
                    0.9873460531234741
                ],
                [
                    523.523193359375,
                    997.3013916015625,
                    0.965083122253418
                ],
                [
                    362.9604797363281,
                    1147.3017578125,
                    0.9676201939582825
                ],
                [
                    591.7939453125,
                    977.8621826171875,
                    0.9600459933280945
                ],
                [
                    624.6943359375,
                    1071.31103515625,
                    0.8626542687416077
                ],
                [
                    609.1981811523438,
                    1016.3128662109375,
                    0.886297345161438
                ],
                [
                    724.1837158203125,
                    1055.94189453125,
                    0.9029495716094971
                ],
                [
                    676.5245971679688,
                    957.1024169921875,
                    0.9183933138847351
                ],
                [
                    767.14599609375,
                    1069.138427734375,
                    0.9375356435775757
                ],
                [
                    737.4354248046875,
                    967.7557373046875,
                    0.9274413585662842
                ]
            ]
        }
    ],
    "categories": [
        {
            "supercategory": "person",
            "id": 1,
            "name": "person",
            "keypoints": [
                "nose",
                "left_eye",
                "right_eye",
                "left_ear",
                "right_ear",
                "left_shoulder",
                "right_shoulder",
                "left_elbow",
                "right_elbow",
                "left_wrist",
                "right_wrist",
                "left_hip",
                "right_hip",
                "left_knee",
                "right_knee",
                "left_ankle",
                "right_ankle"
            ],
            "skeleton": [
                [
                    0,
                    1
                ],
                [
                    0,
                    2
                ],
                [
                    1,
                    3
                ],
                [
                    2,
                    4
                ],
                [
                    0,
                    5
                ],
                [
                    0,
                    6
                ],
                [
                    5,
                    7
                ],
                [
                    6,
                    8
                ],
                [
                    7,
                    9
                ],
                [
                    8,
                    10
                ],
                [
                    5,
                    11
                ],
                [
                    6,
                    12
                ],
                [
                    11,
                    13
                ],
                [
                    12,
                    14
                ],
                [
                    13,
                    15
                ],
                [
                    14,
                    16
                ]
            ]
        }
    ]
}