{
    "info": {
        "description": "2D pose estimation outputs from NTU_RGB+D_120",
        "url": "",
        "version": "1.0",
        "year": 2024,
        "contributor": "cacaoBrain-HumanCV",
        "date_created": "2024-03-26 11:28:56"
    },
    "video": {
        "path": "./NTU_DATASET/A085/S019C002P051R001A085_rgb.avi",
        "width": 1920,
        "height": 1080,
        "original_length": 79,
        "fps": 30.0
    },
    "annotations": [
        {
            "0": [
                [
                    475.14532470703125,
                    834.0689697265625,
                    0.9771043658256531
                ],
                [
                    465.0281677246094,
                    842.3311767578125,
                    0.9688664078712463
                ],
                [
                    466.8499450683594,
                    832.773193359375,
                    0.9377864003181458
                ],
                [
                    468.397216796875,
                    873.3193359375,
                    0.9725021719932556
                ],
                [
                    471.6330871582031,
                    858.7886962890625,
                    0.673316240310669
                ],
                [
                    535.5731811523438,
                    897.940673828125,
                    0.9244868159294128
                ],
                [
                    532.6353759765625,
                    861.2651977539062,
                    0.8688194751739502
                ],
                [
                    625.3779296875,
                    906.955322265625,
                    0.9770911931991577
                ],
                [
                    610.6593017578125,
                    853.0325927734375,
                    0.878132700920105
                ],
                [
                    695.451171875,
                    879.2728271484375,
                    0.9218882322311401
                ],
                [
                    645.3511962890625,
                    821.1070556640625,
                    0.9604295492172241
                ],
                [
                    686.3583984375,
                    891.4766235351562,
                    0.8241610527038574
                ],
                [
                    683.3426513671875,
                    867.111572265625,
                    0.7899070978164673
                ],
                [
                    804.658935546875,
                    895.5894775390625,
                    0.9023886322975159
                ],
                [
                    800.8118896484375,
                    887.8114013671875,
                    0.8631315231323242
                ],
                [
                    921.615478515625,
                    911.861572265625,
                    0.9109534621238708
                ],
                [
                    894.728271484375,
                    897.5679321289062,
                    0.9160155653953552
                ]
            ]
        },
        {
            "0": [
                [
                    475.4347839355469,
                    836.46142578125,
                    0.9983375668525696
                ],
                [
                    465.2716369628906,
                    844.5072631835938,
                    0.994127094745636
                ],
                [
                    467.1418151855469,
                    834.648681640625,
                    0.9713935256004333
                ],
                [
                    467.8497009277344,
                    876.177490234375,
                    0.9917572140693665
                ],
                [
                    471.3277587890625,
                    858.86083984375,
                    0.6563736796379089
                ],
                [
                    535.2244873046875,
                    896.3088989257812,
                    0.9265549182891846
                ],
                [
                    530.97705078125,
                    864.9725341796875,
                    0.8349224328994751
                ],
                [
                    627.8890380859375,
                    882.36474609375,
                    0.9593526721000671
                ],
                [
                    613.6649780273438,
                    857.0551147460938,
                    0.8802095055580139
                ],
                [
                    689.85302734375,
                    838.6088256835938,
                    0.9359316825866699
                ],
                [
                    643.7565307617188,
                    820.5391235351562,
                    0.948175311088562
                ],
                [
                    686.7151489257812,
                    893.3171997070312,
                    0.8716124892234802
                ],
                [
                    683.29345703125,
                    874.2275390625,
                    0.7861477732658386
                ],
                [
                    803.9599609375,
                    896.3405151367188,
                    0.91173255443573
                ],
                [
                    798.3719482421875,
                    888.8685913085938,
                    0.8615165948867798
                ],
                [
                    921.9195556640625,
                    911.33740234375,
                    0.8869268298149109
                ],
                [
                    894.925048828125,
                    897.8514404296875,
                    0.9029724597930908
                ]
            ]
        },
        {
            "0": [
                [
                    475.675048828125,
                    838.7416381835938,
                    0.9858959317207336
                ],
                [
                    465.8706359863281,
                    846.7105712890625,
                    0.9831419587135315
                ],
                [
                    467.238525390625,
                    837.38720703125,
                    0.9453348517417908
                ],
                [
                    469.2483825683594,
                    877.732421875,
                    0.993198812007904
                ],
                [
                    471.75439453125,
                    862.5362548828125,
                    0.6874707937240601
                ],
                [
                    534.3789672851562,
                    892.749755859375,
                    0.9115419983863831
                ],
                [
                    530.10791015625,
                    869.977294921875,
                    0.8435081839561462
                ],
                [
                    622.916259765625,
                    873.7537841796875,
                    0.916800856590271
                ],
                [
                    610.968017578125,
                    858.495361328125,
                    0.8934693336486816
                ],
                [
                    681.9063720703125,
                    824.2645263671875,
                    0.9589815139770508
                ],
                [
                    642.4066162109375,
                    822.075927734375,
                    0.9641394019126892
                ],
                [
                    684.8125,
                    889.8516845703125,
                    0.851227879524231
                ],
                [
                    682.2728271484375,
                    873.4166870117188,
                    0.7799070477485657
                ],
                [
                    803.9722290039062,
                    895.1968383789062,
                    0.9042730331420898
                ],
                [
                    799.038330078125,
                    889.0684204101562,
                    0.855864942073822
                ],
                [
                    922.3125,
                    911.4833374023438,
                    0.8974823951721191
                ],
                [
                    894.7923583984375,
                    898.1931762695312,
                    0.9021363258361816
                ]
            ]
        },
        {
            "0": [
                [
                    475.51580810546875,
                    838.162109375,
                    0.9976528882980347
                ],
                [
                    465.5155334472656,
                    845.7022705078125,
                    1.0019543170928955
                ],
                [
                    466.7933044433594,
                    837.3109130859375,
                    0.9659204483032227
                ],
                [
                    467.88775634765625,
                    876.8170776367188,
                    0.971622109413147
                ],
                [
                    470.2687683105469,
                    866.9149169921875,
                    0.7351982593536377
                ],
                [
                    533.0865478515625,
                    889.1515502929688,
                    0.9086599349975586
                ],
                [
                    527.7527465820312,
                    874.5607299804688,
                    0.7941922545433044
                ],
                [
                    624.4688720703125,
                    875.0275268554688,
                    0.9658612608909607
                ],
                [
                    608.48486328125,
                    867.135986328125,
                    0.883680522441864
                ],
                [
                    676.2550048828125,
                    824.0358276367188,
                    0.936732828617096
                ],
                [
                    637.9616088867188,
                    828.742919921875,
                    0.9362198114395142
                ],
                [
                    683.221435546875,
                    885.60205078125,
                    0.8615425825119019
                ],
                [
                    680.1998291015625,
                    871.8536987304688,
                    0.7658583521842957
                ],
                [
                    802.2462768554688,
                    893.48388671875,
                    0.896828830242157
                ],
                [
                    797.875,
                    887.775390625,
                    0.8564513325691223
                ],
                [
                    922.3499755859375,
                    911.3502197265625,
                    0.9018272161483765
                ],
                [
                    895.335693359375,
                    897.4152221679688,
                    0.8966968655586243
                ]
            ]
        },
        {
            "0": [
                [
                    480.0791015625,
                    837.0451049804688,
                    0.9683634042739868
                ],
                [
                    469.4998779296875,
                    842.8073120117188,
                    0.9996967911720276
                ],
                [
                    470.1803894042969,
                    837.1060791015625,
                    0.9327293634414673
                ],
                [
                    470.0043029785156,
                    871.6663208007812,
                    0.9899681210517883
                ],
                [
                    470.9873046875,
                    867.32470703125,
                    0.749583899974823
                ],
                [
                    534.9048461914062,
                    885.7584228515625,
                    0.9162710905075073
                ],
                [
                    525.8798828125,
                    881.057861328125,
                    0.7458100318908691
                ],
                [
                    625.2308959960938,
                    875.5183715820312,
                    0.9775620698928833
                ],
                [
                    606.5618896484375,
                    871.3674926757812,
                    0.8417155742645264
                ],
                [
                    667.2896118164062,
                    819.01220703125,
                    0.926766037940979
                ],
                [
                    634.56201171875,
                    830.53955078125,
                    0.9200437664985657
                ],
                [
                    684.5872802734375,
                    882.7718505859375,
                    0.8155264258384705
                ],
                [
                    680.70654296875,
                    874.7471313476562,
                    0.7259593605995178
                ],
                [
                    801.974365234375,
                    891.9033203125,
                    0.864374577999115
                ],
                [
                    798.4000244140625,
                    887.3538208007812,
                    0.8507484793663025
                ],
                [
                    922.5372314453125,
                    911.1512451171875,
                    0.8838132619857788
                ],
                [
                    894.9705810546875,
                    897.3898315429688,
                    0.8798043727874756
                ]
            ]
        },
        {
            "0": [
                [
                    486.54925537109375,
                    834.8387451171875,
                    0.9707684516906738
                ],
                [
                    475.32000732421875,
                    837.6907958984375,
                    0.9781321883201599
                ],
                [
                    476.2338562011719,
                    833.6459350585938,
                    0.9300144910812378
                ],
                [
                    471.2638244628906,
                    863.9463500976562,
                    0.9878256916999817
                ],
                [
                    471.3447265625,
                    866.5543212890625,
                    0.7777655124664307
                ],
                [
                    532.7744750976562,
                    887.0282592773438,
                    0.8934670686721802
                ],
                [
                    524.104736328125,
                    886.7764892578125,
                    0.7864047884941101
                ],
                [
                    619.8462524414062,
                    873.75732421875,
                    1.0044004917144775
                ],
                [
                    611.45068359375,
                    874.045166015625,
                    0.7745459675788879
                ],
                [
                    627.2235107421875,
                    810.0201416015625,
                    0.9348151087760925
                ],
                [
                    619.4222412109375,
                    822.6011962890625,
                    0.9187508225440979
                ],
                [
                    688.484619140625,
                    883.0811767578125,
                    0.8284284472465515
                ],
                [
                    685.2343139648438,
                    878.3855590820312,
                    0.729009211063385
                ],
                [
                    805.650390625,
                    893.9012451171875,
                    0.896502673625946
                ],
                [
                    801.1258544921875,
                    889.9073486328125,
                    0.8486126661300659
                ],
                [
                    921.4922485351562,
                    911.0150146484375,
                    0.886435866355896
                ],
                [
                    896.1446533203125,
                    897.859130859375,
                    0.8780291676521301
                ]
            ]
        },
        {
            "0": [
                [
                    490.767333984375,
                    835.700927734375,
                    0.9456467628479004
                ],
                [
                    479.5818176269531,
                    837.9176025390625,
                    1.0050599575042725
                ],
                [
                    480.63037109375,
                    834.0004272460938,
                    0.9323242902755737
                ],
                [
                    472.9857482910156,
                    862.0659790039062,
                    0.9596670866012573
                ],
                [
                    472.79302978515625,
                    862.569091796875,
                    0.7609001994132996
                ],
                [
                    530.38037109375,
                    891.1696166992188,
                    0.9451752305030823
                ],
                [
                    525.3071899414062,
                    882.9049072265625,
                    0.8315787315368652
                ],
                [
                    616.6705322265625,
                    865.81396484375,
                    0.9870263338088989
                ],
                [
                    602.5211181640625,
                    863.1097412109375,
                    0.799889862537384
                ],
                [
                    598.6830444335938,
                    808.43115234375,
                    0.9641147255897522
                ],
                [
                    615.3413696289062,
                    811.9561767578125,
                    0.8980995416641235
                ],
                [
                    688.5447998046875,
                    885.2042236328125,
                    0.8624380230903625
                ],
                [
                    686.3896484375,
                    874.518798828125,
                    0.786398708820343
                ],
                [
                    804.7282104492188,
                    894.6807250976562,
                    0.8902097940444946
                ],
                [
                    800.5427856445312,
                    889.4277954101562,
                    0.8438723683357239
                ],
                [
                    921.970703125,
                    911.1436767578125,
                    0.9072663187980652
                ],
                [
                    895.070068359375,
                    897.914306640625,
                    0.8907026648521423
                ]
            ]
        },
        {
            "0": [
                [
                    490.9962158203125,
                    834.6311645507812,
                    0.958637535572052
                ],
                [
                    479.4416198730469,
                    835.946533203125,
                    0.9784625172615051
                ],
                [
                    480.7654724121094,
                    832.5682373046875,
                    0.9399288296699524
                ],
                [
                    472.70159912109375,
                    861.43994140625,
                    0.9892955422401428
                ],
                [
                    472.6861267089844,
                    863.2620849609375,
                    0.7623094916343689
                ],
                [
                    531.547607421875,
                    890.0870971679688,
                    0.8814723491668701
                ],
                [
                    522.9361572265625,
                    888.2801513671875,
                    0.7850116491317749
                ],
                [
                    616.5519409179688,
                    860.7196044921875,
                    0.9825353622436523
                ],
                [
                    601.707763671875,
                    866.5636596679688,
                    0.7049126625061035
                ],
                [
                    601.6842651367188,
                    812.5274047851562,
                    0.9743812084197998
                ],
                [
                    604.1591796875,
                    818.0667114257812,
                    0.8404182195663452
                ],
                [
                    689.8525390625,
                    885.1519775390625,
                    0.8422408103942871
                ],
                [
                    686.4759521484375,
                    880.68310546875,
                    0.7040472626686096
                ],
                [
                    805.777587890625,
                    894.7769775390625,
                    0.8943517208099365
                ],
                [
                    801.3251953125,
                    890.711669921875,
                    0.8429031372070312
                ],
                [
                    922.0980224609375,
                    910.6599731445312,
                    0.8840362429618835
                ],
                [
                    896.1632080078125,
                    898.1171875,
                    0.8516414165496826
                ]
            ]
        },
        {
            "0": [
                [
                    491.615478515625,
                    834.7821044921875,
                    0.9782882928848267
                ],
                [
                    479.771240234375,
                    835.6337280273438,
                    1.006133794784546
                ],
                [
                    480.81097412109375,
                    832.708740234375,
                    0.9345430731773376
                ],
                [
                    472.6023864746094,
                    859.6019897460938,
                    0.9948141574859619
                ],
                [
                    472.21881103515625,
                    861.275146484375,
                    0.7812160849571228
                ],
                [
                    532.9119262695312,
                    889.2247314453125,
                    0.9217129349708557
                ],
                [
                    525.9911499023438,
                    882.4270629882812,
                    0.7891669869422913
                ],
                [
                    618.7535400390625,
                    875.0450439453125,
                    0.987790048122406
                ],
                [
                    604.1864013671875,
                    868.7571411132812,
                    0.7457565665245056
                ],
                [
                    604.539794921875,
                    821.40283203125,
                    0.9360592365264893
                ],
                [
                    605.400390625,
                    823.1774291992188,
                    0.9248316287994385
                ],
                [
                    690.276611328125,
                    885.0823974609375,
                    0.8477555513381958
                ],
                [
                    687.2742309570312,
                    875.6813354492188,
                    0.7308393120765686
                ],
                [
                    806.47802734375,
                    894.6041870117188,
                    0.8977611064910889
                ],
                [
                    801.96337890625,
                    889.1517333984375,
                    0.8614287376403809
                ],
                [
                    921.916015625,
                    911.3071899414062,
                    0.8889811635017395
                ],
                [
                    895.9968872070312,
                    896.917724609375,
                    0.9030155539512634
                ]
            ]
        },
        {
            "0": [
                [
                    489.303955078125,
                    831.61279296875,
                    0.9847145080566406
                ],
                [
                    477.9917907714844,
                    834.2348022460938,
                    0.9754568934440613
                ],
                [
                    478.92822265625,
                    830.4888916015625,
                    0.9349604249000549
                ],
                [
                    472.54150390625,
                    857.9884033203125,
                    0.9941405653953552
                ],
                [
                    472.3879699707031,
                    858.5147094726562,
                    0.7660219073295593
                ],
                [
                    532.3992309570312,
                    891.8736572265625,
                    0.9430402517318726
                ],
                [
                    528.2313842773438,
                    875.65478515625,
                    0.8299614787101746
                ],
                [
                    616.1807250976562,
                    883.262451171875,
                    0.9673267006874084
                ],
                [
                    601.9154663085938,
                    866.7291870117188,
                    0.8235712051391602
                ],
                [
                    578.2398681640625,
                    833.48095703125,
                    0.945446789264679
                ],
                [
                    618.1983032226562,
                    823.6694946289062,
                    0.9759979844093323
                ],
                [
                    689.814697265625,
                    886.2214965820312,
                    0.8508557081222534
                ],
                [
                    687.2384033203125,
                    872.5045776367188,
                    0.8012886643409729
                ],
                [
                    805.203369140625,
                    893.9849853515625,
                    0.8981536030769348
                ],
                [
                    800.7379150390625,
                    887.7603759765625,
                    0.8336590528488159
                ],
                [
                    921.4385375976562,
                    912.0322265625,
                    0.8922290802001953
                ],
                [
                    895.6348876953125,
                    896.7882080078125,
                    0.8930278420448303
                ]
            ]
        },
        {
            "0": [
                [
                    491.3145446777344,
                    832.82763671875,
                    0.9579415321350098
                ],
                [
                    479.2364196777344,
                    833.93115234375,
                    1.0028780698776245
                ],
                [
                    481.1148986816406,
                    830.5133056640625,
                    0.9223618507385254
                ],
                [
                    472.2682800292969,
                    859.2899780273438,
                    0.9814919233322144
                ],
                [
                    472.4598388671875,
                    860.9397583007812,
                    0.6874215602874756
                ],
                [
                    534.23095703125,
                    900.5050048828125,
                    0.8899877667427063
                ],
                [
                    528.7848510742188,
                    874.8731689453125,
                    0.8534435033798218
                ],
                [
                    608.25048828125,
                    858.5337524414062,
                    0.9608522653579712
                ],
                [
                    604.5669555664062,
                    865.484375,
                    0.8207127451896667
                ],
                [
                    541.856201171875,
                    838.4635620117188,
                    0.9839993715286255
                ],
                [
                    622.88623046875,
                    826.33984375,
                    0.9353390336036682
                ],
                [
                    691.026123046875,
                    887.67236328125,
                    0.8592547178268433
                ],
                [
                    687.9336547851562,
                    871.1231689453125,
                    0.7942031025886536
                ],
                [
                    804.70849609375,
                    895.5081176757812,
                    0.8873769044876099
                ],
                [
                    800.1278076171875,
                    888.1468505859375,
                    0.8756701350212097
                ],
                [
                    921.7315673828125,
                    911.712646484375,
                    0.870093584060669
                ],
                [
                    894.8514404296875,
                    897.7513427734375,
                    0.9033578634262085
                ]
            ]
        },
        {
            "0": [
                [
                    493.29608154296875,
                    833.5628662109375,
                    0.9737546443939209
                ],
                [
                    481.5964660644531,
                    835.2078857421875,
                    0.9750407934188843
                ],
                [
                    484.0464782714844,
                    830.51416015625,
                    0.9337306618690491
                ],
                [
                    473.1878662109375,
                    861.048095703125,
                    0.9653112292289734
                ],
                [
                    474.6365661621094,
                    859.5794677734375,
                    0.6373692750930786
                ],
                [
                    533.60986328125,
                    900.3607788085938,
                    0.895194411277771
                ],
                [
                    526.1722412109375,
                    875.33447265625,
                    0.8042851090431213
                ],
                [
                    600.3046875,
                    848.17431640625,
                    1.0172255039215088
                ],
                [
                    600.794921875,
                    866.8201293945312,
                    0.8233595490455627
                ],
                [
                    536.0167846679688,
                    841.2098999023438,
                    0.9967215061187744
                ],
                [
                    624.4226684570312,
                    827.2132568359375,
                    0.9378506541252136
                ],
                [
                    690.0859375,
                    887.014892578125,
                    0.8420162796974182
                ],
                [
                    687.3198852539062,
                    870.9422607421875,
                    0.7803956866264343
                ],
                [
                    804.4730834960938,
                    894.6639404296875,
                    0.8737698197364807
                ],
                [
                    800.25830078125,
                    888.2958984375,
                    0.8728254437446594
                ],
                [
                    922.0186767578125,
                    911.5170288085938,
                    0.9038041234016418
                ],
                [
                    894.490478515625,
                    897.3843383789062,
                    0.9074487090110779
                ]
            ]
        },
        {
            "0": [
                [
                    488.90789794921875,
                    832.1968383789062,
                    0.9743253588676453
                ],
                [
                    476.6343994140625,
                    834.9293823242188,
                    0.9729802012443542
                ],
                [
                    478.9249267578125,
                    829.7850341796875,
                    0.943082869052887
                ],
                [
                    469.3834533691406,
                    862.849853515625,
                    0.9965525269508362
                ],
                [
                    471.3335876464844,
                    857.5664672851562,
                    0.6845097541809082
                ],
                [
                    535.8201904296875,
                    899.2511596679688,
                    0.8932462334632874
                ],
                [
                    529.6636962890625,
                    878.7051391601562,
                    0.792503297328949
                ],
                [
                    612.1318359375,
                    857.178466796875,
                    0.9783722162246704
                ],
                [
                    604.3558349609375,
                    865.5284423828125,
                    0.7950010299682617
                ],
                [
                    553.3275146484375,
                    845.137451171875,
                    1.000132441520691
                ],
                [
                    626.2750244140625,
                    826.9507446289062,
                    0.9758062958717346
                ],
                [
                    690.2742919921875,
                    887.3802490234375,
                    0.8615221381187439
                ],
                [
                    687.7093505859375,
                    872.2125244140625,
                    0.7799978852272034
                ],
                [
                    804.08447265625,
                    894.9057006835938,
                    0.8929904103279114
                ],
                [
                    799.6700439453125,
                    888.1001586914062,
                    0.8791994452476501
                ],
                [
                    921.9248046875,
                    911.7471923828125,
                    0.8837952613830566
                ],
                [
                    895.588134765625,
                    898.3946533203125,
                    0.9150342345237732
                ]
            ]
        },
        {
            "0": [
                [
                    489.630126953125,
                    831.85595703125,
                    0.9410860538482666
                ],
                [
                    477.3541564941406,
                    834.6986083984375,
                    0.9839529991149902
                ],
                [
                    479.9303283691406,
                    829.676513671875,
                    0.9382001757621765
                ],
                [
                    469.67132568359375,
                    862.5208740234375,
                    0.999287486076355
                ],
                [
                    472.25201416015625,
                    858.2042236328125,
                    0.6604534983634949
                ],
                [
                    535.047119140625,
                    898.8436279296875,
                    0.8795458078384399
                ],
                [
                    528.7965087890625,
                    878.07861328125,
                    0.7796300649642944
                ],
                [
                    604.1937255859375,
                    849.5856323242188,
                    0.9691674709320068
                ],
                [
                    602.9419555664062,
                    866.3759765625,
                    0.7940797209739685
                ],
                [
                    542.1729736328125,
                    841.4563598632812,
                    0.9683917760848999
                ],
                [
                    626.1517944335938,
                    827.753173828125,
                    0.9879206418991089
                ],
                [
                    690.107666015625,
                    886.4613037109375,
                    0.8526049852371216
                ],
                [
                    687.7467041015625,
                    872.0629272460938,
                    0.7898624539375305
                ],
                [
                    804.580078125,
                    894.7073974609375,
                    0.8669666051864624
                ],
                [
                    800.144775390625,
                    888.4715576171875,
                    0.8804367184638977
                ],
                [
                    921.86767578125,
                    911.0292358398438,
                    0.8937261700630188
                ],
                [
                    894.8523559570312,
                    897.7681274414062,
                    0.9199771881103516
                ]
            ]
        },
        {
            "0": [
                [
                    489.0699157714844,
                    830.9970703125,
                    0.9628716111183167
                ],
                [
                    476.8643493652344,
                    834.9304809570312,
                    0.9838989973068237
                ],
                [
                    479.4418640136719,
                    829.0418701171875,
                    0.9471949934959412
                ],
                [
                    470.5673522949219,
                    864.0755004882812,
                    0.9931898713111877
                ],
                [
                    473.5107727050781,
                    858.551025390625,
                    0.6466564536094666
                ],
                [
                    534.20703125,
                    898.3172607421875,
                    0.882445752620697
                ],
                [
                    526.6072387695312,
                    876.585205078125,
                    0.7866392731666565
                ],
                [
                    601.2529907226562,
                    843.3670654296875,
                    1.024409532546997
                ],
                [
                    601.0130615234375,
                    864.6058349609375,
                    0.8406657576560974
                ],
                [
                    537.9859619140625,
                    840.717041015625,
                    1.0114527940750122
                ],
                [
                    624.789306640625,
                    826.0842895507812,
                    0.9703974723815918
                ],
                [
                    689.4708862304688,
                    886.5213623046875,
                    0.8402899503707886
                ],
                [
                    687.001708984375,
                    871.3284912109375,
                    0.7834757566452026
                ],
                [
                    804.3441162109375,
                    894.6331787109375,
                    0.859216034412384
                ],
                [
                    799.7927856445312,
                    888.3152465820312,
                    0.8730424046516418
                ],
                [
                    922.660400390625,
                    911.7733154296875,
                    0.9019266366958618
                ],
                [
                    894.0048828125,
                    897.2161865234375,
                    0.9094979166984558
                ]
            ]
        },
        {
            "0": [
                [
                    488.32257080078125,
                    830.7488403320312,
                    0.9906595945358276
                ],
                [
                    476.5912780761719,
                    833.711181640625,
                    0.9997076988220215
                ],
                [
                    478.21484375,
                    829.7080078125,
                    0.9269919395446777
                ],
                [
                    471.322998046875,
                    862.4612426757812,
                    0.9724169373512268
                ],
                [
                    473.12451171875,
                    861.5731201171875,
                    0.736823320388794
                ],
                [
                    534.0889282226562,
                    895.0240478515625,
                    0.8933793306350708
                ],
                [
                    528.641845703125,
                    876.7646484375,
                    0.8280125856399536
                ],
                [
                    613.87109375,
                    863.06103515625,
                    0.9721883535385132
                ],
                [
                    599.3381958007812,
                    863.5902099609375,
                    0.7695336937904358
                ],
                [
                    563.4781494140625,
                    837.9026489257812,
                    1.0064743757247925
                ],
                [
                    615.4400024414062,
                    822.719970703125,
                    0.9595052003860474
                ],
                [
                    689.4196166992188,
                    885.3455810546875,
                    0.8456541895866394
                ],
                [
                    686.5767822265625,
                    871.1117553710938,
                    0.754643440246582
                ],
                [
                    805.1119384765625,
                    894.1160888671875,
                    0.88255375623703
                ],
                [
                    801.5211181640625,
                    888.26708984375,
                    0.8509731292724609
                ],
                [
                    922.957275390625,
                    911.2999267578125,
                    0.9104369878768921
                ],
                [
                    894.658203125,
                    897.7269287109375,
                    0.8777905702590942
                ]
            ]
        },
        {
            "0": [
                [
                    487.431640625,
                    829.0706787109375,
                    0.9774598479270935
                ],
                [
                    475.7803039550781,
                    833.7598876953125,
                    1.0014488697052002
                ],
                [
                    477.3512878417969,
                    827.5181274414062,
                    0.9711942672729492
                ],
                [
                    472.0682373046875,
                    861.573486328125,
                    0.9756345748901367
                ],
                [
                    473.4272155761719,
                    858.3675537109375,
                    0.7728704214096069
                ],
                [
                    530.923828125,
                    886.65478515625,
                    0.9367209672927856
                ],
                [
                    527.5799560546875,
                    873.2269897460938,
                    0.8386515378952026
                ],
                [
                    614.6076049804688,
                    893.6506958007812,
                    0.9763681292533875
                ],
                [
                    598.269287109375,
                    864.1500854492188,
                    0.8303122520446777
                ],
                [
                    603.174072265625,
                    833.0836791992188,
                    0.9088466167449951
                ],
                [
                    571.5386352539062,
                    821.9911499023438,
                    0.9455780982971191
                ],
                [
                    689.1648559570312,
                    883.7042236328125,
                    0.8551076054573059
                ],
                [
                    686.7876586914062,
                    871.5419921875,
                    0.8002021908760071
                ],
                [
                    805.3610229492188,
                    894.02587890625,
                    0.8746710419654846
                ],
                [
                    800.9076538085938,
                    887.998779296875,
                    0.8586714267730713
                ],
                [
                    921.3150634765625,
                    912.1324462890625,
                    0.8871436715126038
                ],
                [
                    894.6732177734375,
                    897.9002685546875,
                    0.889356255531311
                ]
            ]
        },
        {
            "0": [
                [
                    490.3855285644531,
                    827.607421875,
                    0.9798930883407593
                ],
                [
                    479.90203857421875,
                    831.1480712890625,
                    1.0059945583343506
                ],
                [
                    480.59832763671875,
                    825.5204467773438,
                    0.9326258301734924
                ],
                [
                    475.6295166015625,
                    860.3306274414062,
                    0.9659237265586853
                ],
                [
                    476.9248962402344,
                    858.1469116210938,
                    0.6872102618217468
                ],
                [
                    530.7613525390625,
                    882.7924194335938,
                    0.9531446099281311
                ],
                [
                    523.0494384765625,
                    872.3533935546875,
                    0.7698801159858704
                ],
                [
                    611.381103515625,
                    902.6494140625,
                    0.9796543121337891
                ],
                [
                    597.5670776367188,
                    848.6976928710938,
                    0.9417905807495117
                ],
                [
                    635.5650634765625,
                    836.2937622070312,
                    1.0036667585372925
                ],
                [
                    541.8963012695312,
                    832.1295166015625,
                    0.9602595567703247
                ],
                [
                    687.859619140625,
                    882.3450927734375,
                    0.8394501805305481
                ],
                [
                    684.1915893554688,
                    872.6422729492188,
                    0.7319125533103943
                ],
                [
                    803.3701782226562,
                    892.9541625976562,
                    0.8881343007087708
                ],
                [
                    799.8021240234375,
                    887.3563232421875,
                    0.8392531275749207
                ],
                [
                    922.28564453125,
                    910.833251953125,
                    0.8980059027671814
                ],
                [
                    897.0165405273438,
                    896.5850830078125,
                    0.8822488188743591
                ]
            ]
        },
        {
            "0": [
                [
                    489.3965759277344,
                    827.2850341796875,
                    0.9752370119094849
                ],
                [
                    478.89990234375,
                    830.6572875976562,
                    1.0102728605270386
                ],
                [
                    479.80413818359375,
                    825.78662109375,
                    0.9194804430007935
                ],
                [
                    475.0452575683594,
                    859.154296875,
                    0.9607511758804321
                ],
                [
                    475.9494934082031,
                    857.9202880859375,
                    0.7204017043113708
                ],
                [
                    530.6613159179688,
                    881.5552368164062,
                    0.9363341331481934
                ],
                [
                    523.3533935546875,
                    871.1651611328125,
                    0.7579553127288818
                ],
                [
                    610.9965209960938,
                    903.291748046875,
                    0.9845563173294067
                ],
                [
                    596.5133056640625,
                    843.355712890625,
                    0.8800032138824463
                ],
                [
                    646.9503784179688,
                    838.5997924804688,
                    1.0036365985870361
                ],
                [
                    550.07080078125,
                    836.6122436523438,
                    0.9410368800163269
                ],
                [
                    686.0466918945312,
                    882.461669921875,
                    0.8307270407676697
                ],
                [
                    682.4041748046875,
                    870.6702270507812,
                    0.7256277799606323
                ],
                [
                    802.513916015625,
                    892.8604736328125,
                    0.8871394991874695
                ],
                [
                    798.9588623046875,
                    887.4154663085938,
                    0.8346351981163025
                ],
                [
                    922.1678466796875,
                    911.0321044921875,
                    0.8969870805740356
                ],
                [
                    896.1818237304688,
                    896.5159912109375,
                    0.8657380938529968
                ]
            ]
        },
        {
            "0": [
                [
                    487.7581787109375,
                    828.785888671875,
                    0.9737916588783264
                ],
                [
                    477.07574462890625,
                    832.0333251953125,
                    1.0042277574539185
                ],
                [
                    477.41339111328125,
                    827.58740234375,
                    0.9308881759643555
                ],
                [
                    474.4400634765625,
                    859.3047485351562,
                    0.9218022227287292
                ],
                [
                    475.14593505859375,
                    857.6809692382812,
                    0.6903353929519653
                ],
                [
                    530.8870849609375,
                    882.4365234375,
                    0.9196045994758606
                ],
                [
                    524.0421752929688,
                    869.1578979492188,
                    0.7552671432495117
                ],
                [
                    611.025390625,
                    905.2034912109375,
                    0.9472527503967285
                ],
                [
                    598.2240600585938,
                    845.7938842773438,
                    0.9354550242424011
                ],
                [
                    650.349853515625,
                    840.4088745117188,
                    0.9912452101707458
                ],
                [
                    548.880615234375,
                    832.5394287109375,
                    0.9682852625846863
                ],
                [
                    685.8833618164062,
                    883.4764404296875,
                    0.8456335067749023
                ],
                [
                    682.17431640625,
                    870.75634765625,
                    0.7232053279876709
                ],
                [
                    803.873046875,
                    893.6586303710938,
                    0.8571910858154297
                ],
                [
                    800.229736328125,
                    887.9351806640625,
                    0.8427517414093018
                ],
                [
                    921.180908203125,
                    911.531982421875,
                    0.9179454445838928
                ],
                [
                    895.9051513671875,
                    896.64013671875,
                    0.8816474676132202
                ]
            ]
        },
        {
            "0": [
                [
                    489.01629638671875,
                    828.894287109375,
                    0.982186496257782
                ],
                [
                    478.12396240234375,
                    832.0955200195312,
                    1.0038567781448364
                ],
                [
                    478.6359558105469,
                    826.8939208984375,
                    0.935546338558197
                ],
                [
                    474.8014221191406,
                    860.5264892578125,
                    0.9321902990341187
                ],
                [
                    476.2913818359375,
                    856.6578979492188,
                    0.6616168022155762
                ],
                [
                    531.344482421875,
                    883.404296875,
                    0.9348400235176086
                ],
                [
                    525.140869140625,
                    866.9942626953125,
                    0.7772774696350098
                ],
                [
                    612.601806640625,
                    904.2333984375,
                    0.9640250205993652
                ],
                [
                    591.6143798828125,
                    840.4566650390625,
                    0.9445775151252747
                ],
                [
                    652.049072265625,
                    838.903564453125,
                    0.9914021492004395
                ],
                [
                    545.5201416015625,
                    831.3379516601562,
                    0.9674443006515503
                ],
                [
                    686.3841552734375,
                    883.2008056640625,
                    0.8418683409690857
                ],
                [
                    682.5964965820312,
                    868.8757934570312,
                    0.7303280830383301
                ],
                [
                    803.6700439453125,
                    892.7048950195312,
                    0.8832611441612244
                ],
                [
                    800.3311157226562,
                    886.7139892578125,
                    0.8365300893783569
                ],
                [
                    922.732177734375,
                    910.95654296875,
                    0.9094783067703247
                ],
                [
                    895.9927978515625,
                    896.3956298828125,
                    0.8698691129684448
                ]
            ]
        },
        {
            "0": [
                [
                    486.8730773925781,
                    829.8443603515625,
                    0.9695441722869873
                ],
                [
                    476.23138427734375,
                    833.220458984375,
                    0.9944426417350769
                ],
                [
                    476.55206298828125,
                    827.8116455078125,
                    0.917611300945282
                ],
                [
                    473.5052185058594,
                    862.0948486328125,
                    0.9084332585334778
                ],
                [
                    475.3264465332031,
                    858.14599609375,
                    0.6796079277992249
                ],
                [
                    530.348876953125,
                    886.4512939453125,
                    0.9349648952484131
                ],
                [
                    525.0872192382812,
                    870.752685546875,
                    0.7650150656700134
                ],
                [
                    612.3753051757812,
                    901.6529541015625,
                    0.9655285477638245
                ],
                [
                    601.0889892578125,
                    852.8170166015625,
                    0.9110947251319885
                ],
                [
                    637.5933227539062,
                    832.9661865234375,
                    0.9914631843566895
                ],
                [
                    561.661376953125,
                    834.1087646484375,
                    0.9620490670204163
                ],
                [
                    686.0361328125,
                    885.1346435546875,
                    0.8374044299125671
                ],
                [
                    682.6357421875,
                    869.855712890625,
                    0.7455016374588013
                ],
                [
                    803.7769775390625,
                    893.619140625,
                    0.8667393922805786
                ],
                [
                    800.2833251953125,
                    887.4078369140625,
                    0.8457366228103638
                ],
                [
                    922.3477783203125,
                    911.3812866210938,
                    0.9094437956809998
                ],
                [
                    895.5517578125,
                    896.941162109375,
                    0.8849436640739441
                ]
            ]
        },
        {
            "0": [
                [
                    488.61993408203125,
                    831.14794921875,
                    0.9591941833496094
                ],
                [
                    477.8590087890625,
                    836.6309814453125,
                    1.0104883909225464
                ],
                [
                    478.78338623046875,
                    829.2630615234375,
                    0.9579617977142334
                ],
                [
                    474.56915283203125,
                    867.3306274414062,
                    0.9624441862106323
                ],
                [
                    476.0049743652344,
                    861.524169921875,
                    0.7411827445030212
                ],
                [
                    530.778076171875,
                    891.1447143554688,
                    0.948281466960907
                ],
                [
                    529.6292724609375,
                    871.59326171875,
                    0.8450940847396851
                ],
                [
                    607.59375,
                    878.037109375,
                    0.9705138802528381
                ],
                [
                    600.8546752929688,
                    868.1134033203125,
                    0.7946771383285522
                ],
                [
                    576.749267578125,
                    816.3009033203125,
                    0.9301973581314087
                ],
                [
                    588.1065063476562,
                    820.9159545898438,
                    0.8440686464309692
                ],
                [
                    690.2821655273438,
                    886.7628173828125,
                    0.8469988107681274
                ],
                [
                    688.8330078125,
                    870.7135620117188,
                    0.7945868968963623
                ],
                [
                    805.873046875,
                    895.20703125,
                    0.8773090839385986
                ],
                [
                    802.231201171875,
                    889.041015625,
                    0.8778387308120728
                ],
                [
                    920.8649291992188,
                    912.6114501953125,
                    0.8862561583518982
                ],
                [
                    896.0508422851562,
                    897.79248046875,
                    0.8982135653495789
                ]
            ]
        },
        {
            "0": [
                [
                    486.12957763671875,
                    834.5673217773438,
                    0.9604916572570801
                ],
                [
                    475.3152770996094,
                    841.2701416015625,
                    1.0007275342941284
                ],
                [
                    476.3431091308594,
                    832.9830322265625,
                    0.9606122970581055
                ],
                [
                    472.909912109375,
                    872.7167358398438,
                    0.9828535914421082
                ],
                [
                    475.8650817871094,
                    864.2595825195312,
                    0.6900125741958618
                ],
                [
                    528.3192138671875,
                    892.13427734375,
                    0.943504810333252
                ],
                [
                    528.2545166015625,
                    873.1519165039062,
                    0.8309877514839172
                ],
                [
                    602.6217041015625,
                    859.6895141601562,
                    0.9930458664894104
                ],
                [
                    600.8206787109375,
                    870.2672119140625,
                    0.7839767336845398
                ],
                [
                    558.6175537109375,
                    818.1351318359375,
                    0.924858033657074
                ],
                [
                    630.28759765625,
                    837.2169189453125,
                    0.9273061156272888
                ],
                [
                    686.447998046875,
                    887.6056518554688,
                    0.8497644662857056
                ],
                [
                    685.0989990234375,
                    872.0784912109375,
                    0.7607740759849548
                ],
                [
                    805.177490234375,
                    895.8345336914062,
                    0.8536544442176819
                ],
                [
                    801.7813720703125,
                    889.6583251953125,
                    0.8574249148368835
                ],
                [
                    922.6119384765625,
                    911.9423217773438,
                    0.921847403049469
                ],
                [
                    895.855712890625,
                    897.5188598632812,
                    0.8935443758964539
                ]
            ]
        },
        {
            "0": [
                [
                    478.3815612792969,
                    837.5292358398438,
                    0.9855843782424927
                ],
                [
                    468.4910583496094,
                    845.8643188476562,
                    0.9785507917404175
                ],
                [
                    469.5770263671875,
                    835.64208984375,
                    0.957375705242157
                ],
                [
                    470.4051818847656,
                    878.14404296875,
                    0.9730076193809509
                ],
                [
                    473.0503845214844,
                    862.5003662109375,
                    0.6459788680076599
                ],
                [
                    530.2022705078125,
                    889.999755859375,
                    0.9070462584495544
                ],
                [
                    528.3685302734375,
                    869.9951782226562,
                    0.7870796322822571
                ],
                [
                    612.5399169921875,
                    869.7227783203125,
                    0.9603472948074341
                ],
                [
                    598.0415649414062,
                    863.246826171875,
                    0.7639527320861816
                ],
                [
                    592.2190551757812,
                    822.0047607421875,
                    0.942050039768219
                ],
                [
                    635.2666015625,
                    838.5667114257812,
                    0.8891635537147522
                ],
                [
                    686.7040405273438,
                    886.876953125,
                    0.8448915481567383
                ],
                [
                    684.8073120117188,
                    870.3992919921875,
                    0.7598485946655273
                ],
                [
                    805.104248046875,
                    895.1757202148438,
                    0.8570922613143921
                ],
                [
                    801.5801391601562,
                    889.1277465820312,
                    0.8696660399436951
                ],
                [
                    922.6910400390625,
                    911.729736328125,
                    0.9225193858146667
                ],
                [
                    895.9232788085938,
                    897.1114501953125,
                    0.8990480899810791
                ]
            ]
        },
        {
            "0": [
                [
                    474.68438720703125,
                    839.3285522460938,
                    1.0011235475540161
                ],
                [
                    464.8568420410156,
                    848.113525390625,
                    0.9954456686973572
                ],
                [
                    466.1009216308594,
                    837.7902221679688,
                    0.9836994409561157
                ],
                [
                    468.945068359375,
                    879.4765625,
                    0.9602001309394836
                ],
                [
                    471.453369140625,
                    863.368896484375,
                    0.6587162613868713
                ],
                [
                    529.9482421875,
                    887.7774658203125,
                    0.8997676372528076
                ],
                [
                    526.3853149414062,
                    872.5223388671875,
                    0.7950925827026367
                ],
                [
                    616.910400390625,
                    885.45361328125,
                    0.9676344394683838
                ],
                [
                    609.3004760742188,
                    872.3072509765625,
                    0.7818867564201355
                ],
                [
                    643.814208984375,
                    824.6648559570312,
                    0.9565529823303223
                ],
                [
                    648.1880493164062,
                    832.9697875976562,
                    0.7946446537971497
                ],
                [
                    687.5263671875,
                    885.88720703125,
                    0.8386424779891968
                ],
                [
                    685.1986694335938,
                    871.310791015625,
                    0.7579313516616821
                ],
                [
                    806.5927124023438,
                    895.08544921875,
                    0.8589792847633362
                ],
                [
                    802.511962890625,
                    889.4701538085938,
                    0.8298518061637878
                ],
                [
                    922.0874633789062,
                    912.2882080078125,
                    0.9102532863616943
                ],
                [
                    895.5903930664062,
                    898.0042114257812,
                    0.8949151635169983
                ]
            ]
        },
        {
            "0": [
                [
                    475.62921142578125,
                    839.7437744140625,
                    1.0013049840927124
                ],
                [
                    465.84674072265625,
                    847.9840698242188,
                    0.9899702072143555
                ],
                [
                    466.62103271484375,
                    838.2493896484375,
                    0.9673900604248047
                ],
                [
                    468.6666564941406,
                    878.7158203125,
                    0.9684781432151794
                ],
                [
                    470.8546142578125,
                    867.4566650390625,
                    0.6079697608947754
                ],
                [
                    530.86767578125,
                    887.9358520507812,
                    0.8866773843765259
                ],
                [
                    524.270751953125,
                    874.5521240234375,
                    0.7970291972160339
                ],
                [
                    616.7954711914062,
                    893.979248046875,
                    0.9382678270339966
                ],
                [
                    601.3715209960938,
                    871.0814819335938,
                    0.7928702235221863
                ],
                [
                    666.091064453125,
                    838.810302734375,
                    0.908032238483429
                ],
                [
                    632.0243530273438,
                    836.8720703125,
                    0.9764971137046814
                ],
                [
                    684.4263305664062,
                    887.8601684570312,
                    0.8191497921943665
                ],
                [
                    681.1314697265625,
                    874.9635620117188,
                    0.7491896748542786
                ],
                [
                    803.9974365234375,
                    895.048095703125,
                    0.8790620565414429
                ],
                [
                    799.4522705078125,
                    888.6586303710938,
                    0.8111510872840881
                ],
                [
                    922.4678344726562,
                    911.80419921875,
                    0.8954325318336487
                ],
                [
                    895.8419189453125,
                    897.5049438476562,
                    0.8644443154335022
                ]
            ]
        }
    ],
    "categories": [
        {
            "supercategory": "person",
            "id": 1,
            "name": "person",
            "keypoints": [
                "nose",
                "left_eye",
                "right_eye",
                "left_ear",
                "right_ear",
                "left_shoulder",
                "right_shoulder",
                "left_elbow",
                "right_elbow",
                "left_wrist",
                "right_wrist",
                "left_hip",
                "right_hip",
                "left_knee",
                "right_knee",
                "left_ankle",
                "right_ankle"
            ],
            "skeleton": [
                [
                    0,
                    1
                ],
                [
                    0,
                    2
                ],
                [
                    1,
                    3
                ],
                [
                    2,
                    4
                ],
                [
                    0,
                    5
                ],
                [
                    0,
                    6
                ],
                [
                    5,
                    7
                ],
                [
                    6,
                    8
                ],
                [
                    7,
                    9
                ],
                [
                    8,
                    10
                ],
                [
                    5,
                    11
                ],
                [
                    6,
                    12
                ],
                [
                    11,
                    13
                ],
                [
                    12,
                    14
                ],
                [
                    13,
                    15
                ],
                [
                    14,
                    16
                ]
            ]
        }
    ]
}